{"title":"【花语】-菖蒲","date":"2010-11-13T09:46:41.000Z","slug":"cloves-changpu","updated":"2019-06-03T10:34:38.439Z","content":"<h2 id=\"妖\">妖<a href=\"post/cloves-changpu#妖\"></a></h2><p>菖蒲，相信者的幸福。</p>\n<p>一丛丛的狗尾草无限的延伸。我也不知疲倦的一直走，连疲累的感觉都没有。</p>\n<p>忘记了时间，忘记了回忆。</p>\n<p>就这样。直到我走进了一片蓝紫色的花海。</p>\n<p>又是无边无际的地方，很远的地方，有一个模糊的人影。不知方向的我，便朝向那个模糊的人影走去。</p>\n<p>近了，是一个短发的女孩。耳朵上插着一朵精致的蓝紫色小花，与这片花海相互呼应。</p>\n<p>女子轻轻偏转精致的面孔看向我，嘴角轻浅的笑，只是看着我，却不说话。</p>\n<p>于是我问：我该如何走？</p>\n<p>大人到此不需要歇息一下吗？</p>\n<p>我在世间行走，依然习惯。</p>\n<p>大人，可知菖蒲花语，相信者的幸福？</p>\n<p>嗯，知道，相信着，就会幸福。若去怀疑，那么，徒增痛苦。</p>\n<p>可是大人，如今还相信什么？</p>\n<p>不知道，如今无所谓相信，而是要知道一切。</p>\n<p>大人，下雪了。</p>\n<p>我抬头，确实下雪了，这雪下的突然。</p>\n<p>为何会下雪？我问道。</p>\n<p>那花妖便告诉我，天地间有异动，有不合常理之事发生，五行错乱，才生了这异象。</p>\n<p>我不解的看看她。何为异象?</p>\n<p>大人你可能不记得，大人世间行走已经几千年，那之前因为异象频生，导致整个人间都乱了。</p>\n<p>因为我？</p>\n<p>确是与大人有原因，但也是大人结束了动荡，还了人间一个平静。</p>\n<p>我摇摇头，表示没有任何印象。</p>\n<p>大人，天生异象，妖星当道，大人，您，也应该回复真身了。</p>\n<p>我的真身？</p>\n<p>这不也正是大人一直追寻要知道的吗？</p>\n<p>我点点头。</p>\n<p>大人，相信着，便是幸福的，大人，菖蒲渡您一途。</p>\n<p>只见那女子双手扬起，周围细碎的紫色花瓣聚拢在我身下，御风而起，而我，也跟着塌风而走。</p>\n<p>之后，再没听到那女子说话。</p>\n<p>下一处，我将到什么地方？</p>\n<h2 id=\"花\">花<a href=\"post/cloves-changpu#花\"></a></h2><p>我是修行七百年的花妖，说是修行，确是拜一妖所赐，乌鸦，传说她是三足乌的本相，数千年前为了一个人，留在人间。</p>\n<p>她助我，确也是为了一个人。</p>\n<p>天空中黑羽降下。</p>\n<p>她来了。</p>\n<p>身后传来细碎的声响，想必是翅膀收拢的声音。</p>\n<p>而她却低头不语。</p>\n<p>我继续坐在地上，摘面前的紫色小花在手里编织。</p>\n<p>展翅的声音，翅膀挥动的声音，她走了。</p>\n<p>我抬头，看到天空中，宽大的黑色翅膀，随风而动的长发，原本长及脚踝的黑色长发，不知为何，有白色掺杂其中。</p>\n<p>世间，大乱降至！</p>\n","prev":{"title":"asp.net后台执行js造成样式失效","slug":"asp-net后台执行js造成样式失效"},"next":{"title":"被遗忘的运算符(??)","slug":"被遗忘的运算符"},"link":"http://ojdev.github.io/post/cloves-changpu/","toc":[{"title":"妖","id":"妖","index":"1"},{"title":"花","id":"花","index":"2"}]}